{
  "users": [
    {
      "id": 1,
      "username": "Demitchy",
      "about": "Lorem ipsum dolor sit amengilla urna, porttitor rhoncus  in ornare quam viverra",
      "collabs": "Active",
      "avatar": "/assests/images/Avatar/01.png",
      "available": "Web3",
      "category": "Web3 , Advisory , infl..."
    },
    {
      "id": 2,
      "username": "CryptoLord NE",
      "about": "Lorem ipsum dolor sit amengilla urna, porttitor rhoncus  in ornare quam viverra",
      "collabs": "Active",
      "avatar": "/assests/images/Avatar/02.png",
      "available": "Web3",
      "category": "Content creator , Infl."
    },
    {
      "id": 3,
      "username": "Jeffy",
      "about": "Lorem ipsum dolor sit amengilla urna, porttitor rhoncus  in ornare quam viverra",
      "collabs": "Active",
      "avatar": "/assests/images/Avatar/03.png",
      "available": "Web3",
      "category": "Content creator , Infl."
    },
    {
      "id": 4,
      "username": "Xeusthegreat",
      "about": "Lorem ipsum dolor sit amengilla urna, porttitor rhoncus  in ornare quam viverra",
      "collabs": "Active",
      "avatar": "/assests/images/Avatar/04.png",
      "available": "Web3",
      "category": "Content creator , Infl."
    },
    {
      "id": 5,
      "username": "CryptoCoach",
      "about": "Lorem ipsum dolor sit amengilla urna, porttitor rhoncus  in ornare quam viverra",
      "collabs": "Active",
      "avatar": "/assests/images/Avatar/05.png",
      "available": "Web3",
      "category": "Content creator , Infl."
    },
    {
      "id": 6,
      "username": "Korex",
      "about": "Lorem ipsum dolor sit amengilla urna, porttitor rhoncus  in ornare quam viverra",
      "collabs": "Active",
      "avatar": "/assests/images/Avatar/06.png",
      "available": "Web3",
      "category": "Content creator , Infl."
    },
    {
      "id": 7,
      "username": "ZukaDev",
      "about": "Lorem ipsum dolor sit amengilla urna, porttitor rhoncus  in ornare quam viverra",
      "collabs": "Active",
      "avatar": "/assests/images/Avatar/07.png",
      "available": "Web3",
      "category": "Content creator , Infl."
    },
    {
      "id": 8,
      "username": "Olawale",
      "about": "Lorem ipsum dolor sit amengilla urna, porttitor rhoncus  in ornare quam viverra",
      "collabs": "Active",
      "avatar": "/assests/images/Avatar/08.png",
      "available": "Web3",
      "category": "Content creator , Infl."
    },
    {
      "id": 9,
      "username": "Haropis",
      "about": "Lorem ipsum dolor sit amengilla urna, porttitor rhoncus  in ornare quam viverra",
      "collabs": "Active",
      "avatar": "/assests/images/Avatar/09.png",
      "available": "Web3",
      "category": "Content creator , Infl."
    },
    {
      "id": 10,
      "username": "Kaiser",
      "about": "Lorem ipsum dolor sit amengilla urna, porttitor rhoncus  in ornare quam viverra",
      "collabs": "Active",
      "avatar": "/assests/images/Avatar/10.png",
      "available": "Web3",
      "category": "Content creator , Infl."
    },
    {
      "id": 11,
      "username": "Ugo",
      "about": "Lorem ipsum dolor sit amengilla urna, porttitor rhoncus  in ornare quam viverra",
      "collabs": "Active",
      "avatar": "/assests/images/Avatar/11.png",
      "available": "Web3",
      "category": "Content creator , Infl."
    },
    {
      "id": 12,
      "username": "Alexa",
      "about": "Lorem ipsum dolor sit amengilla urna, porttitor rhoncus  in ornare quam viverra",
      "collabs": "Active",
      "avatar": "/assests/images/Avatar/12.png",
      "available": "Web3",
      "category": "Content creator , Infl."
    },
    {
      "id": 13,
      "username": "Tunde Ednut",
      "about": "Lorem ipsum dolor sit amengilla urna, porttitor rhoncus  in ornare quam viverra",
      "collabs": "Active",
      "avatar": "/assests/images/Avatar/13.png",
      "available": "Web3",
      "category": "Content creator , Infl."
    },
    {
      "id": 14,
      "username": "Odogwu",
      "about": "Lorem ipsum dolor sit amengilla urna, porttitor rhoncus  in ornare quam viverra",
      "avatar": "/assests/images/Avatar/14.png",
      "collabs": "Active",
      "available": "Web3",
      "category": "Content creator , Infl."
    },
    {
      "id": 15,
      "username": "BigWiz",
      "about": "Lorem ipsum dolor sit amengilla urna, porttitor rhoncus  in ornare quam viverra",
      "avatar": "/assests/images/Avatar/15.png",
      "collabs": "Active",
      "available": "Web3",
      "category": "Content creator , Infl."
    },
    {
      "id": 16,
      "username": "Olawale",
      "about": "Lorem ipsum dolor sit amengilla urna, porttitor rhoncus  in ornare quam viverra",
      "collabs": "Active",
      "avatar": "/assests/images/Avatar/16.png",
      "available": "Web3",
      "category": "Content creator , Infl."
    },
    {
      "id": 17,
      "username": "Ugo",
      "about": "Lorem ipsum dolor sit amengilla urna, porttitor rhoncus  in ornare quam viverra",
      "collabs": "Active",
      "avatar": "/assests/images/Avatar/17.png",
      "available": "Web3",
      "category": "Content creator , Infl."
    },
    {
      "id": 18,
      "username": "Alexa",
      "about": "Lorem ipsum dolor sit amengilla urna, porttitor rhoncus  in ornare quam viverra",
      "collabs": "Active",
      "avatar": "/assests/images/Avatar/18.png",
      "available": "Web3",
      "category": "Content creator , Infl."
    },
    {
      "id": 19,
      "username": "Tunde Ednut",
      "about": "Lorem ipsum dolor sit amengilla urna, porttitor rhoncus  in ornare quam viverra",
      "collabs": "Active",
      "avatar": "/assests/images/Avatar/19.png",
      "available": "Web3",
      "category": "Content creator , Infl."
    },
    {
      "id": 20,
      "username": "Odogwu",
      "about": "Lorem ipsum dolor sit amengilla urna, porttitor rhoncus  in ornare quam viverra",
      "avatar": "/assests/images/Avatar/20.png",
      "collabs": "Active",
      "available": "Web3",
      "category": "Content creator , Infl."
    },
    {
      "id": 21,
      "username": "BigWiz",
      "about": "Lorem ipsum dolor sit amengilla urna, porttitor rhoncus  in ornare quam viverra",
      "avatar": "/assests/images/Avatar/21.png",
      "collabs": "Active",
      "available": "Web3",
      "category": "Content creator , Infl."
    },
    {
      "id": 22,
      "username": "Olawale",
      "about": "Lorem ipsum dolor sit amengilla urna, porttitor rhoncus  in ornare quam viverra",
      "collabs": "Active",
      "avatar": "/assests/images/Avatar/22.png",
      "available": "Web3",
      "category": "Content creator , Infl."
    },
    {
      "id": 23,
      "username": "Demitchy",
      "about": "Lorem ipsum dolor sit amengilla urna, porttitor rhoncus  in ornare quam viverra",
      "collabs": "Active",
      "avatar": "/assests/images/Avatar/23.png",
      "available": "Web3",
      "category": "Web3 , Advisory , infl..."
    },
    {
      "id": 24,
      "username": "CryptoLord NE",
      "about": "Lorem ipsum dolor sit amengilla urna, porttitor rhoncus  in ornare quam viverra",
      "collabs": "Active",
      "avatar": "/assests/images/Avatar/24.png",
      "available": "Web3",
      "category": "Content creator , Infl."
    },
    {
      "id": 25,
      "username": "Jeffy",
      "about": "Lorem ipsum dolor sit amengilla urna, porttitor rhoncus  in ornare quam viverra",
      "collabs": "Active",
      "avatar": "/assests/images/Avatar/03.png",
      "available": "Web3",
      "category": "Content creator , Infl."
    },
    {
      "id": 26,
      "username": "Xeusthegreat",
      "about": "Lorem ipsum dolor sit amengilla urna, porttitor rhoncus  in ornare quam viverra",
      "collabs": "Active",
      "avatar": "/assests/images/Avatar/04.png",
      "available": "Web3",
      "category": "Content creator , Infl."
    },
    {
      "id": 27,
      "username": "CryptoCoach",
      "about": "Lorem ipsum dolor sit amengilla urna, porttitor rhoncus  in ornare quam viverra",
      "collabs": "Active",
      "avatar": "/assests/images/Avatar/05.png",
      "available": "Web3",
      "category": "Content creator , Infl."
    },
    {
      "id": 28,
      "username": "Korex",
      "about": "Lorem ipsum dolor sit amengilla urna, porttitor rhoncus  in ornare quam viverra",
      "collabs": "Active",
      "avatar": "/assests/images/Avatar/06.png",
      "available": "Web3",
      "category": "Content creator , Infl."
    },
    {
      "id": 28,
      "username": "ZukaDev",
      "about": "Lorem ipsum dolor sit amengilla urna, porttitor rhoncus  in ornare quam viverra",
      "collabs": "Active",
      "avatar": "/assests/images/Avatar/07.png",
      "available": "Web3",
      "category": "Content creator , Infl."
    },
    {
      "id": 29,
      "username": "Olawale",
      "about": "Lorem ipsum dolor sit amengilla urna, porttitor rhoncus  in ornare quam viverra",
      "collabs": "Active",
      "avatar": "/assests/images/Avatar/08.png",
      "available": "Web3",
      "category": "Content creator , Infl."
    },
    {
      "id": 30,
      "username": "Haropis",
      "about": "Lorem ipsum dolor sit amengilla urna, porttitor rhoncus  in ornare quam viverra",
      "collabs": "Active",
      "avatar": "/assests/images/Avatar/09.png",
      "available": "Web3",
      "category": "Content creator , Infl."
    },
    {
      "id": 31,
      "username": "Kaiser",
      "about": "Lorem ipsum dolor sit amengilla urna, porttitor rhoncus  in ornare quam viverra",
      "collabs": "Active",
      "avatar": "/assests/images/Avatar/10.png",
      "available": "Web3",
      "category": "Content creator , Infl."
    }
  ],
  "organizations": [
    {
      "id": 1,
      "name": "WHO",
      "about": "Lorem ipsum dolor sit amengilla urna, porttitor rhoncus  in ornare quam viverra",
      "collabs": "Active",
      "avatar": "/assests/images/Avatar/01.png",
      "available": "Web3",
      "category": "Web3 , Advisory , infl..."
    },
    {
      "id": 2,
      "name": "FIFA",
      "about": "Lorem ipsum dolor sit amengilla urna, porttitor rhoncus  in ornare quam viverra",
      "collabs": "Active",
      "avatar": "/assests/images/Avatar/01.png",
      "available": "Web3",
      "category": "Web3 , Advisory , infl..."
    },
    {
      "id": 3,
      "name": "EFCC",
      "about": "Lorem ipsum dolor sit amengilla urna, porttitor rhoncus  in ornare quam viverra",
      "collabs": "Active",
      "avatar": "/assests/images/Avatar/01.png",
      "available": "Web3",
      "category": "Web3 , Advisory , infl..."
    },
    {
      "id": 4,
      "name": "E-FOOTBALL",
      "about": "Lorem ipsum dolor sit amengilla urna, porttitor rhoncus  in ornare quam viverra",
      "collabs": "Active",
      "avatar": "/assests/images/Avatar/01.png",
      "available": "Web3",
      "category": "Web3 , Advisory , infl..."
    },
    {
      "id": 5,
      "name": "NAFDAC",
      "about": "Lorem ipsum dolor sit amengilla urna, porttitor rhoncus  in ornare quam viverra",
      "collabs": "Active",
      "avatar": "/assests/images/Avatar/01.png",
      "available": "Web3",
      "category": "Web3 , Advisory , infl..."
    },
    {
      "id": 6,
      "name": "NDLEA",
      "about": "Lorem ipsum dolor sit amengilla urna, porttitor rhoncus  in ornare quam viverra",
      "collabs": "Active",
      "avatar": "/assests/images/Avatar/01.png",
      "available": "Web3",
      "category": "Web3 , Advisory , infl..."
    },
    {
      "id": 7,
      "name": "NYPD",
      "about": "Lorem ipsum dolor sit amengilla urna, porttitor rhoncus  in ornare quam viverra",
      "collabs": "Active",
      "avatar": "/assests/images/Avatar/01.png",
      "available": "Web3",
      "category": "Web3 , Advisory , infl..."
    },
    {
      "id": 8,
      "name": "SWAT",
      "about": "Lorem ipsum dolor sit amengilla urna, porttitor rhoncus  in ornare quam viverra",
      "collabs": "Active",
      "avatar": "/assests/images/Avatar/01.png",
      "available": "Web3",
      "category": "Web3 , Advisory , infl..."
    },
    {
      "id": 9,
      "name": "NBA",
      "about": "Lorem ipsum dolor sit amengilla urna, porttitor rhoncus  in ornare quam viverra",
      "collabs": "Active",
      "avatar": "/assests/images/Avatar/01.png",
      "available": "Web3",
      "category": "Web3 , Advisory , infl..."
    }
  ],
  "services": [
    {
      "id": 1,
      "name": "Python programming",
      "about": "Lorem ipsum dolor sit amengilla urna, porttitor rhoncus  in ornare quam viverra",
      "rating": 4.5,
      "price": 4000,
      "tags": ["Python", "Programming"]
    },
    {
      "id": 2,
      "name": "Machine learning",
      "about": "Lorem ipsum dolor sit amengilla urna, porttitor rhoncus  in ornare quam viverra",
      "rating": 4.5,
      "price": 4000,
      "tags": ["Machine learning", "AI"]
    },
    {
      "id": 3,
      "name": "Web development",
      "about": "Lorem ipsum dolor sit amengilla urna, porttitor rhoncus  in ornare quam viverra",
      "rating": 4.5,
      "price": 4000,
      "tags": [
        "React JS",
        "Next JS",
        "Node JS",
        "Python",
        "Flask",
        "Web",
        "Programming"
      ]
    },
    {
      "id": 4,
      "name": "Mobile app development",
      "about": "Lorem ipsum dolor sit amengilla urna, porttitor rhoncus  in ornare quam viverra",
      "rating": 4.5,
      "price": 4000,
      "tags": [
        "Dart",
        "Flutter",
        "React native",
        "Kotlin",
        "Mobile",
        "Programming"
      ]
    },
    {
      "id": 5,
      "name": "Desktop development",
      "about": "Lorem ipsum dolor sit amengilla urna, porttitor rhoncus  in ornare quam viverra",
      "rating": 4.5,
      "price": 4000,
      "tags": ["C++", "C#", "Tkinter", "Python", "Programming"]
    },
    {
      "id": 6,
      "name": "Product design",
      "about": "Lorem ipsum dolor sit amengilla urna, porttitor rhoncus  in ornare quam viverra",
      "rating": 4.5,
      "price": 4000,
      "tags": ["UI", "UX", "Figma", "Design"]
    }
  ],
  "products": [
    {
      "id": 1,
      "name": "Airpods pro",
      "price": 4000,
      "rating": 4,
      "about": "Lorem ipsum dolor sit amengilla urna, porttitor rhoncus  in ornare quam viverra",
      "tags": ["Apple", "Gadgets", "Electronics"]
    },
    {
      "id": 2,
      "name": "ACER Alienware X360",
      "price": 4000,
      "rating": 4,
      "about": "Lorem ipsum dolor sit amengilla urna, porttitor rhoncus  in ornare quam viverra",
      "tags": ["HP", "Windows", "PC", "Laptop", "Gadgets", "Electronics"]
    },
    {
      "id": 3,
      "name": "HP Probook X360",
      "price": 4000,
      "rating": 4,
      "about": "Lorem ipsum dolor sit amengilla urna, porttitor rhoncus  in ornare quam viverra",
      "tags": ["HP", "Windows", "PC", "Laptop", "Gadgets", "Electronics"]
    },
    {
      "id": 4,
      "name": "Macbook Air",
      "price": 4000,
      "rating": 4,
      "about": "Lorem ipsum dolor sit amengilla urna, porttitor rhoncus  in ornare quam viverra",
      "tags": ["Apple", "Macbook", "PC", "Gadgets", "Electronics"]
    }
  ],
  "collab": [
    {
      "id": 1,
      "role": "Marketing manager",
      "firm": "Okay bears",
      "location": "Lagos, Nigeria",
      "about": "Lorem ipsum dolor sit amengilla urna, porttitor rhoncus  in ornare quam viverra",
      "is_full_time": true,
      "is_paid": true,
      "posted_on": "03-08-23",
      "num_applications": 100,
      "tags": ["Marketing", "Marketing expert", "Managing"]
    },
    {
      "id": 2,
      "role": "Human Relations Manager",
      "firm": "Leadway",
      "location": "Abuja, Nigeria",
      "about": "Lorem ipsum dolor sit amengilla urna, porttitor rhoncus  in ornare quam viverra",
      "is_full_time": true,
      "is_paid": true,
      "posted_on": "03-08-23",
      "num_applications": 100,
      "tags": ["Relations", "Managing"]
    },
    {
      "id": 3,
      "role": "Managing Director",
      "firm": "Okay bears",
      "location": "Lagos, Nigeria",
      "about": "Lorem ipsum dolor sit amengilla urna, porttitor rhoncus  in ornare quam viverra",
      "is_full_time": true,
      "is_paid": true,
      "posted_on": "03-08-23",
      "num_applications": 100,
      "tags": ["Director", "Supervision", "Managing"]
    },
    {
      "id": 4,
      "role": "Inter-personal Relations manager",
      "firm": "The App Brewery",
      "location": "England, UK",
      "about": "Lorem ipsum dolor sit amengilla urna, porttitor rhoncus  in ornare quam viverra",
      "is_full_time": true,
      "is_paid": true,
      "posted_on": "03-08-23",
      "num_applications": 100,
      "tags": ["Relations", "Managing"]
    },
    {
      "id": 5,
      "role": "Chief Operating Officer",
      "firm": "Free World",
      "location": "PH, Nigeria",
      "about": "Lorem ipsum dolor sit amengilla urna, porttitor rhoncus  in ornare quam viverra",
      "is_full_time": true,
      "is_paid": true,
      "posted_on": "03-08-23",
      "num_applications": 100,
      "tags": ["Supervision", "Managing"]
    },
    {
      "id": 6,
      "role": "Project Manager",
      "firm": "The Jacobians",
      "location": "Lagos, Nigeria",
      "about": "Lorem ipsum dolor sit amengilla urna, porttitor rhoncus  in ornare quam viverra",
      "is_full_time": true,
      "is_paid": true,
      "posted_on": "03-08-23",
      "num_applications": 100,
      "tags": ["Project", "Supervision", "Managing"]
    }
  ]
}
