{
  "proposals": [
    {
      "id": 1,
      "from": "8bit",
      "to": "OkayBears",
      "sender": "Demitchy",
      "receiver": "Collab team",
      "type": "Patnership",
      "status": "Delivered",
      "category": "default"
    },
    {
      "id": 2,
      "from": "Primates",
      "to": "Gm DAO",
      "sender": "Solfada",
      "receiver": "Somas",
      "type": "Sponsorship",
      "status": "Inview",
      "category": "new"
    },
    {
      "id": 3,
      "from": "Froots",
      "to": "Rekt DAO",
      "sender": "mitch",
      "receiver": "Bronte",
      "type": "Job Opportunity",
      "status": "Completed",
      "category": "accepted"
    }
  ]
}
